adatasets/__init__.py
adatasets/adatasets.py
adatasets/ztest.py
adatasets-0.1.16295265.dist-info/LICENSE
adatasets-0.1.16295265.dist-info/METADATA
adatasets-0.1.16295265.dist-info/WHEEL
adatasets-0.1.16295265.dist-info/entry_points.txt
adatasets-0.1.16295265.dist-info/top_level.txt
adatasets-0.1.16295265.dist-info/RECORD
